falstart/__init__.py
falstart/__main__.py
falstart/falstart.py
falstart/local_provision.py
falstart/settings.py
falstart/templates/Makefile.j2
falstart/templates/Vagrantfile.j2
falstart/templates/celery.j2
falstart/templates/coveragerc.j2
falstart/templates/gitignore.j2
falstart/templates/lintrc.j2
falstart/templates/provision_fabfile.j2
falstart/templates/requirements.j2
falstart/templates/settings_local.j2
falstart/templates/includes/app.j2
falstart/templates/includes/app_init.j2
falstart/templates/includes/common.j2
falstart/templates/includes/database.j2
falstart/templates/includes/head.j2
falstart/templates/includes/nginx.j2
falstart/templates/py_codes/celery.j2
falstart/templates/py_codes/celery_init.j2
falstart/templates/py_codes/settings_local.j2
falstart/templates/py_codes/settings_tail.j2
falstart/templates/vagrant_templates/environment.j2
falstart/templates/vagrant_templates/locale.gen.j2
falstart/templates/vagrant_templates/nginx-host.j2
falstart-0.2.2.data/data/LICENSE
falstart-0.2.2.data/data/README.rst
falstart-0.2.2.dist-info/DESCRIPTION.rst
falstart-0.2.2.dist-info/METADATA
falstart-0.2.2.dist-info/RECORD
falstart-0.2.2.dist-info/WHEEL
falstart-0.2.2.dist-info/entry_points.txt
falstart-0.2.2.dist-info/metadata.json
falstart-0.2.2.dist-info/top_level.txt
